setup.cfg
setup.py
cashier/__init__.py
cashier.egg-info/PKG-INFO
cashier.egg-info/SOURCES.txt
cashier.egg-info/dependency_links.txt
cashier.egg-info/top_level.txt