Metadata-Version: 1.1
Name: cashier
Version: 1.2
Summary: Caching for python functions
Home-page: http://atmb4u.github.io/cashier
Author: Anoop Thomas Mathew
Author-email: atmb4u@gmail.com
License: BSD
Platform: UNKNOWN
Classifier: Programming Language :: Python
Classifier: Programming Language :: Python :: 2.7
Classifier: Programming Language :: Python :: 3.5
Classifier: License :: OSI Approved :: BSD License
Classifier: Operating System :: OS Independent
Classifier: Intended Audience :: Developers
Classifier: Environment :: Console
Classifier: Topic :: Software Development :: Libraries :: Python Modules
